setup.py
src/simpleweb/BUGS
src/simpleweb/ChangeLog
src/simpleweb/TODO
src/simpleweb/__init__.py
src/simpleweb/_urls.py
src/simpleweb/app.py
src/simpleweb/dispatcher.py
src/simpleweb/middleware.py
src/simpleweb/settings.py
src/simpleweb/utils.py
src/simpleweb/webserver.py
src/simpleweb.egg-info/PKG-INFO
src/simpleweb.egg-info/SOURCES.txt
src/simpleweb.egg-info/dependency_links.txt
src/simpleweb.egg-info/entry_points.txt
src/simpleweb.egg-info/requires.txt
src/simpleweb.egg-info/top_level.txt
src/simpleweb/admin/__init__.py
src/simpleweb/admin/console.py
src/simpleweb/admin/plugins/__init__.py
src/simpleweb/admin/plugins/create_movable.py
src/simpleweb/admin/plugins/create_project.py
src/simpleweb/admin/plugins/create_tables.py
src/simpleweb/admin/plugins/drop_tables.py
src/simpleweb/admin/plugins/help.py
src/simpleweb/admin/plugins/run.py
src/simpleweb/admin/plugins/templates.py
src/simpleweb/admin/plugins/test/test_create_movable.py
src/simpleweb/extlib/__init__.py
src/simpleweb/extlib/memento.py
src/simpleweb/extlib/resolver.py
src/simpleweb/extlib/selector.py
src/simpleweb/extlib/static.py
src/simpleweb/extlib/yaro.py
src/simpleweb/plugins/__init__.py
src/simpleweb/plugins/auth.py
src/simpleweb/plugins/dblayer.py
src/simpleweb/plugins/runmethods.py
src/simpleweb/plugins/template.py
src/simpleweb/test/test_dispatcher.py
src/simpleweb/test/test_settings.py
src/simpleweb/test/test_utils.py
