Metadata-Version: 1.0
Name: simpleweb
Version: 0.7.3
Summary: A simple python wsgi compliant web framework, inspired by Django, Turbo Gears and Web.py
Home-page: http://simpleweb.essienitaessien.com
Author: Essien Ita Essien
Author-email: me@essienitaessien.com
License: BSD
Keywords: web framework simple cheetah sqlobject
Platform: UNKNOWN
